ragxo/__init__.py
ragxo/client.py
ragxo/utils.py
ragxo-0.1.13.dist-info/METADATA
ragxo-0.1.13.dist-info/WHEEL
ragxo-0.1.13.dist-info/RECORD
